fairchem/demo/ocpapi/.isort.cfg
fairchem/demo/ocpapi/LICENSE
fairchem/demo/ocpapi/README.md
fairchem/demo/ocpapi/__init__.py
fairchem/demo/ocpapi/version.py
fairchem/demo/ocpapi/client/__init__.py
fairchem/demo/ocpapi/client/client.py
fairchem/demo/ocpapi/client/models.py
fairchem/demo/ocpapi/client/ui.py
fairchem/demo/ocpapi/workflows/__init__.py
fairchem/demo/ocpapi/workflows/adsorbates.py
fairchem/demo/ocpapi/workflows/context.py
fairchem/demo/ocpapi/workflows/filter.py
fairchem/demo/ocpapi/workflows/log.py
fairchem/demo/ocpapi/workflows/retry.py
fairchem_demo_ocpapi-0.2.0.dist-info/METADATA
fairchem_demo_ocpapi-0.2.0.dist-info/WHEEL
fairchem_demo_ocpapi-0.2.0.dist-info/RECORD
