Metadata-Version: 2.3
Name: fairchem-demo-ocpapi
Version: 0.2.0
Summary: Python client library for the Open Catalyst API
Project-URL: repository, https://github.com/FAIR-Chem/fairchem/tree/main/src/fairchem/demo/ocpapi
Project-URL: home, https://open-catalyst.metademolab.com/
Project-URL: documentation, https://fair-chem.github.io/
Author-email: Open Catalyst Project <opencatalyst@meta.com>
License: MIT License
Classifier: License :: OSI Approved :: MIT License
Classifier: Operating System :: OS Independent
Classifier: Programming Language :: Python :: 3
Requires-Python: >=3.9
Requires-Dist: dataclasses-json==0.6.0
Requires-Dist: inquirer==3.1.3
Requires-Dist: requests==2.32.3
Requires-Dist: responses==0.23.2
Requires-Dist: tenacity==8.2.3
Requires-Dist: tqdm==4.66.1
Provides-Extra: dev
Requires-Dist: ase; extra == 'dev'
Requires-Dist: readchar==4.0.5; extra == 'dev'
